README.md
setup.cfg
setup.py
bin/schavott
schavott/Assembler.py
schavott/MainApp.py
schavott/ReadData.py
schavott/Scaffold.py
schavott/UI.py
schavott/__init__.py
schavott/__main__.py
schavott/gfatofasta.py
schavott.egg-info/PKG-INFO
schavott.egg-info/SOURCES.txt
schavott.egg-info/dependency_links.txt
schavott.egg-info/requires.txt
schavott.egg-info/top_level.txt