Metadata-Version: 1.1
Name: schavott
Version: 0.5.0
Summary: Scaffolding and assembly in real-time
Home-page: http://github.com/emilhaegglund/schavott
Author: Emil Haegglund
Author-email: haegglund.emil@gmail.com
License: MIT
Download-URL: https://github.com/emilhaegglund/schavott/tarball/v0.5.0
Keywords: MinION-sequencing,Bioinformatics,Real-time
Platform: UNKNOWN
Requires: python (>=2.7)
